{"id":"search-items-in-ebay;search-for-items-pilas;chrome-headless-shell-122-0-6261-128;linux","name":"Search for items Pilas","title":"Search for items Pilas","manual":false,"testSteps":[{"number":1,"description":"Given Danny opens the eBay \"https://www.ebay.com/\"","startTime":"2024-03-20T16:16:51.244Z","children":[{"number":2,"description":"Danny navigate to an articles list","startTime":"2024-03-20T16:16:51.250Z","children":[{"number":3,"description":"Danny navigates to 'https://www.ebay.com/'","startTime":"2024-03-20T16:16:51.250Z","children":[],"reportData":[],"screenshots":[{"screenshot":"photo-linux-chrome-headless-shell-122.0.6261.128-danny-navigates-to-h-0156b7cab8.png","screenshotName":"photo-linux-chrome-headless-shell-122.0.6261.128-danny-navigates-to-h-0156b7cab8.png","timeStamp":1710951414717}],"duration":3247,"result":"SUCCESS"},{"number":4,"description":"Danny clicks on Ingresar Articulos a Buscar","startTime":"2024-03-20T16:16:54.725Z","children":[],"reportData":[],"screenshots":[{"screenshot":"photo-linux-chrome-headless-shell-122.0.6261.128-danny-clicks-on-ingre-12a96bc01f.png","screenshotName":"photo-linux-chrome-headless-shell-122.0.6261.128-danny-clicks-on-ingre-12a96bc01f.png","timeStamp":1710951416380}],"duration":1336,"result":"SUCCESS"}],"reportData":[],"screenshots":[],"duration":5139,"result":"SUCCESS"}],"reportData":[],"screenshots":[],"duration":5008,"result":"ERROR","exception":{"errorType":"Error","message":"function timed out, ensure the promise resolves within 5000 milliseconds","stackTrace":[{"declaringClass":"","methodName":"Timeout.<anonymous>()","fileName":"/home/runner/work/webdriverio-serenityjs/webdriverio-serenityjs/node_modules/@cucumber/cucumber/lib/time.js","lineNumber":54},{"declaringClass":"","methodName":"listOnTimeout()","fileName":"node:internal/timers","lineNumber":573},{"declaringClass":"","methodName":"process.processTimers()","fileName":"node:internal/timers","lineNumber":514}]}},{"number":5,"description":"When Danny searches for \"Pilas\"","startTime":"2024-03-20T16:16:56.252Z","children":[],"reportData":[],"screenshots":[],"duration":1,"result":"SKIPPED"},{"number":6,"description":"Then Danny prints the number of items found","startTime":"2024-03-20T16:16:56.253Z","children":[],"reportData":[],"screenshots":[],"duration":0,"result":"SKIPPED"}],"userStory":{"id":"search-items-in-ebay","storyName":"Search items in Ebay","displayName":"Search items in Ebay","path":"ebay/search_articles","type":"feature","narrative":"","pathElements":[{"name":"ebay","description":"Ebay"},{"name":"search_articles","description":"Search articles"}]},"startTime":"2024-03-20T16:16:51.240Z","context":"chrome,linux","driver":"chrome-headless-shell","tags":[{"name":"chrome-headless-shell 122.0.6261.128","type":"browser","browserName":"chrome-headless-shell","browserVersion":"122.0.6261.128","displayName":"chrome-headless-shell 122.0.6261.128"},{"name":"linux","type":"platform","platformName":"linux","platformVersion":"","displayName":"linux"},{"name":"Ebay","type":"capability","displayName":"Ebay"},{"name":"Ebay/Search items in Ebay","type":"feature","displayName":"Search items in Ebay"},{"name":"search","type":"tag","displayName":"search"}],"testSource":"JS","featureTag":{"name":"Ebay/Search items in Ebay","type":"feature","displayName":"Search items in Ebay"},"result":"ERROR","testFailureCause":{"errorType":"Error","message":"function timed out, ensure the promise resolves within 5000 milliseconds","stackTrace":[{"declaringClass":"","methodName":"Timeout.<anonymous>()","fileName":"/home/runner/work/webdriverio-serenityjs/webdriverio-serenityjs/node_modules/@cucumber/cucumber/lib/time.js","lineNumber":54},{"declaringClass":"","methodName":"listOnTimeout()","fileName":"node:internal/timers","lineNumber":573},{"declaringClass":"","methodName":"process.processTimers()","fileName":"node:internal/timers","lineNumber":514}]},"testFailureClassname":"Error","testFailureMessage":"function timed out, ensure the promise resolves within 5000 milliseconds","testFailureSummary":"ERROR;Error;function timed out, ensure the promise resolves within 5000 milliseconds;node:internal/timers","duration":5154}